MANIFEST.in
setup.py
cors/__init__.py
cors/constants.py
cors/cors_application.py
cors/cors_handler.py
cors/cors_options.py
cors/errors.py
cors/filters.py
cors/http_response.py
cors/validators.py
cors_python.egg-info/PKG-INFO
cors_python.egg-info/SOURCES.txt
cors_python.egg-info/dependency_links.txt
cors_python.egg-info/top_level.txt