Metadata-Version: 1.1
Name: cors-python
Version: 0.0.1
Summary: Python CORS Integration for WSGI Applications
Home-page: https://github.com/monsur/cors-python
Author: Monsur Hossain
Author-email: monsur@gmail.com
License: UNKNOWN
Platform: UNKNOWN
Requires: WebOb
